{"cameraMode":{"drawMode":0,"name":"Shaded","section":"Shading Mode"},"sceneLighting":true,"audioPlay":false,"sceneViewState":{"showFog":true,"showMaterialUpdate":false,"showSkybox":true,"showFlares":true,"showImageEffects":true,"showParticleSystems":true},"in2DMode":false,"pivot":{"x":10.424365043640137,"y":4.034228801727295,"z":8.482013702392579},"rotation":{"x":-0.2791542410850525,"y":0.3394051492214203,"z":-0.1062222570180893,"w":-0.8919627070426941},"size":6.98069429397583,"orthographic":false}