{"cameraMode":{"drawMode":0,"name":"Shaded","section":"Shading Mode"},"sceneLighting":false,"audioPlay":false,"sceneViewState":{"showFog":true,"showMaterialUpdate":false,"showSkybox":false,"showFlares":true,"showImageEffects":true,"showParticleSystems":true},"in2DMode":false,"pivot":{"x":0.1910802125930786,"y":0.7991719245910645,"z":0.6010581254959106},"rotation":{"x":-0.15686559677124024,"y":0.6452193856239319,"z":-0.13779714703559876,"w":-0.7351269721984863},"size":2.2863118648529054,"orthographic":false}